{"slug":"anarchos","key":"a)/narxos","head":"ἄναρχος","lemmaBeta":"a)/narxos","count":4,"byWork":[{"work":"Laws","title":"Laws","count":3},{"work":"Republic","title":"Republic","count":1}],"glosses":["without head"],"instancesByWork":[{"work":"Laws","title":"Laws","count":3,"shown":3,"books":[{"book":1,"chapters":[{"chapter":"?","bekker":"","instances":[["639c",4,"ἄναρχον"],["639a",5,"ἄναρχον"]]}]},{"book":12,"chapters":[{"chapter":"?","bekker":"","instances":[["942a",7,"ἄναρχον"]]}]}]},{"work":"Republic","title":"Republic","count":1,"shown":1,"books":[{"book":8,"chapters":[{"chapter":"?","bekker":"","instances":[["558c",4,"ἄναρχος"]]}]}]}],"truncated":false}