{"slug":"argyrion","key":"a)rgu/rion","head":"ἀργύριον","lemmaBeta":"a)rgu/rion","count":62,"byWork":[{"work":"Republic","title":"Republic","count":17},{"work":"HippiasMajor","title":"Hippias Major","count":8},{"work":"Protagoras","title":"Protagoras","count":7},{"work":"Hipparchus","title":"Hipparchus","count":4},{"work":"Meno","title":"Meno","count":4},{"work":"Crito","title":"Crito","count":3},{"work":"Gorgias","title":"Gorgias","count":3},{"work":"Theages","title":"Theages","count":3},{"work":"Apology","title":"Apology","count":2},{"work":"Euthydemus","title":"Euthydemus","count":2},{"work":"Ion","title":"Ion","count":2},{"work":"Letters","title":"Letters","count":2},{"work":"Lysis","title":"Lysis","count":2},{"work":"Alcibiades1","title":"Alcibiades I","count":1},{"work":"Laches","title":"Laches","count":1},{"work":"Theaetetus","title":"Theaetetus","count":1}],"glosses":["small coin, piece of money"],"instancesByWork":[{"work":"Republic","title":"Republic","count":17,"shown":17,"books":[{"book":1,"chapters":[{"chapter":"?","bekker":"","instances":[["333c",5,"ἀργυρίῳ"],["333c",11,"ἀργύριον"],["337d",7,"ἀργύριον"],["337d",9,"ἀργυρίου"],["333b",10,"ἀργυρίου"],["333b",11,"ἀργυρίῳ"],["333b",12,"ἀργυρίου"],["334a",7,"ἀργύριον"],["347a",5,"ἀργύριον"]]}]},{"book":2,"chapters":[{"chapter":"?","bekker":"","instances":[["371d",1,"ἀργυρίου"],["371d",2,"ἀργυρίου"]]}]},{"book":3,"chapters":[{"chapter":"?","bekker":"","instances":[["416e",5,"ἀργύριον"]]}]},{"book":4,"chapters":[{"chapter":"?","bekker":"","instances":[["422d",3,"ἀργυρίῳ"],["442e",6,"ἀργυρίου"]]}]},{"book":6,"chapters":[{"chapter":"?","bekker":"","instances":[["495e",4,"ἀργύριον"]]}]},{"book":8,"chapters":[{"chapter":"?","bekker":"","instances":[["555e",4,"ἀργύριον"]]}]},{"book":9,"chapters":[{"chapter":"?","bekker":"","instances":[["581d",3,"ἀργύριον"]]}]}]},{"work":"HippiasMajor","title":"Hippias Major","count":8,"shown":8,"books":[{"book":1,"chapters":[{"chapter":"?","bekker":"","instances":[["282c",7,"ἀργύριον"],["282d",2,"ἀργύριον"],["282d",3,"ἀργύριον"],["282d",7,"ἀργύριον"],["283d",6,"ἀργυρίου"],["300d",1,"ἀργύριον"],["283b",3,"ἀργύριον"],["283b",5,"ἀργύριον"]]}]}]},{"work":"Protagoras","title":"Protagoras","count":7,"shown":7,"books":[{"book":1,"chapters":[{"chapter":"?","bekker":"","instances":[["310d",7,"ἀργύριον"],["311c",5,"ἀργύριον"],["311d",2,"ἀργύριον"],["357e",7,"ἀργυρίου"],["311b",3,"ἀργύριον"],["311b",7,"ἀργύριον"],["328b",7,"ἀργύριον"]]}]}]},{"work":"Hipparchus","title":"Hipparchus","count":4,"shown":4,"books":[{"book":1,"chapters":[{"chapter":"?","bekker":"","instances":[["231c",9,"ἀργύριον"],["231d",2,"ἀργυρίου"],["231d",8,"ἀργύριον"],["231d",10,"ἀργύριον"]]}]}]},{"work":"Meno","title":"Meno","count":4,"shown":4,"books":[{"book":1,"chapters":[{"chapter":"?","bekker":"","instances":[["78c",7,"ἀργύριον"],["78d",2,"ἀργύριον"],["78e",4,"ἀργύριον"],["92a",8,"ἀργύριον"]]}]}]},{"work":"Crito","title":"Crito","count":3,"shown":3,"books":[{"book":1,"chapters":[{"chapter":"?","bekker":"","instances":[["45a",7,"τἀργύριόν"],["45a",9,"ἀργυρίου"],["45b",4,"ἀργύριον"]]}]}]},{"work":"Gorgias","title":"Gorgias","count":3,"shown":3,"books":[{"book":1,"chapters":[{"chapter":"?","bekker":"","instances":[["520d",1,"ἀργύριον"],["520d",10,"ἀργύριον"],["520e",5,"ἀργύριον"]]}]}]},{"work":"Theages","title":"Theages","count":3,"shown":3,"books":[{"book":1,"chapters":[{"chapter":"?","bekker":"","instances":[["126e",3,"ἀργύριον"],["127a",5,"ἀργύριον"],["128a",6,"ἀργύριον"]]}]}]},{"work":"Apology","title":"Apology","count":2,"shown":2,"books":[{"book":1,"chapters":[{"chapter":"?","bekker":"","instances":[["38b",5,"ἀργυρίου"],["38b",9,"ἀργυρίου"]]}]}]},{"work":"Euthydemus","title":"Euthydemus","count":2,"shown":2,"books":[{"book":1,"chapters":[{"chapter":"?","bekker":"","instances":[["304c",2,"ἀργύριον"],["304a",7,"ἀργύριον"]]}]}]},{"work":"Ion","title":"Ion","count":2,"shown":2,"books":[{"book":1,"chapters":[{"chapter":"?","bekker":"","instances":[["535e",5,"ἀργύριον"],["535e",6,"ἀργύριον"]]}]}]},{"work":"Letters","title":"Letters","count":2,"shown":2,"books":[{"book":1,"chapters":[{"chapter":"?","bekker":"","instances":[["363d",5,"ἀργυρίου"],["361b",4,"Ἀργύριον"]]}]}]},{"work":"Lysis","title":"Lysis","count":2,"shown":2,"books":[{"book":1,"chapters":[{"chapter":"?","bekker":"","instances":[["208b",1,"ἀργύριον"],["220a",2,"ἀργύριον"]]}]}]},{"work":"Alcibiades1","title":"Alcibiades I","count":1,"shown":1,"books":[{"book":1,"chapters":[{"chapter":"?","bekker":"","instances":[["122e",2,"ἀργύριον"]]}]}]},{"work":"Laches","title":"Laches","count":1,"shown":1,"books":[{"book":1,"chapters":[{"chapter":"?","bekker":"","instances":[["192e",3,"ἀργύριον"]]}]}]},{"work":"Theaetetus","title":"Theaetetus","count":1,"shown":1,"books":[{"book":1,"chapters":[{"chapter":"?","bekker":"","instances":[["179a",1,"ἀργύριον"]]}]}]}],"truncated":false}