{"slug":"baros","key":"ba/ros","head":"βάρος","lemmaBeta":"ba/ros","count":9,"byWork":[{"work":"Laws","title":"Laws","count":4},{"work":"Cratylus","title":"Cratylus","count":1},{"work":"Epinomis","title":"Epinomis","count":1},{"work":"Phaedo","title":"Phaedo","count":1},{"work":"Sophist","title":"Sophist","count":1},{"work":"Theaetetus","title":"Theaetetus","count":1}],"glosses":["weight"],"instancesByWork":[{"work":"Laws","title":"Laws","count":4,"shown":4,"books":[{"book":1,"chapters":[{"chapter":"?","bekker":"","instances":[["625d",5,"βάρος"]]}]},{"book":10,"chapters":[{"chapter":"?","bekker":"","instances":[["892b",4,"βαρέων"]]}]},{"book":11,"chapters":[{"chapter":"?","bekker":"","instances":[["925d",6,"βάρος"]]}]},{"book":12,"chapters":[{"chapter":"?","bekker":"","instances":[["945b",7,"βάρους"]]}]}]},{"work":"Cratylus","title":"Cratylus","count":1,"shown":1,"books":[{"book":1,"chapters":[{"chapter":"?","bekker":"","instances":[["419c",7,"βάρει"]]}]}]},{"work":"Epinomis","title":"Epinomis","count":1,"shown":1,"books":[{"book":1,"chapters":[{"chapter":"?","bekker":"","instances":[["988d",3,"βάρος"]]}]}]},{"work":"Phaedo","title":"Phaedo","count":1,"shown":1,"books":[{"book":1,"chapters":[{"chapter":"?","bekker":"","instances":[["117a",9,"βάρος"]]}]}]},{"work":"Sophist","title":"Sophist","count":1,"shown":1,"books":[{"book":1,"chapters":[{"chapter":"?","bekker":"","instances":[["253b",1,"βαρέων"]]}]}]},{"work":"Theaetetus","title":"Theaetetus","count":1,"shown":1,"books":[{"book":1,"chapters":[{"chapter":"?","bekker":"","instances":[["178b",4,"βαρέων"]]}]}]}],"truncated":false}