{"slug":"blapto","key":"bla/ptw","head":"βλάπτω","lemmaBeta":"bla/ptw","count":115,"byWork":[{"work":"Laws","title":"Laws","count":40},{"work":"Republic","title":"Republic","count":25},{"work":"Meno","title":"Meno","count":12},{"work":"Apology","title":"Apology","count":7},{"work":"Alcibiades2","title":"Alcibiades II","count":5},{"work":"Hipparchus","title":"Hipparchus","count":4},{"work":"Letters","title":"Letters","count":4},{"work":"Lysis","title":"Lysis","count":3},{"work":"Alcibiades1","title":"Alcibiades I","count":2},{"work":"Clitophon","title":"Clitophon","count":2},{"work":"Cratylus","title":"Cratylus","count":2},{"work":"Gorgias","title":"Gorgias","count":2},{"work":"HippiasMinor","title":"Hippias Minor","count":2},{"work":"Philebus","title":"Philebus","count":2},{"work":"HippiasMajor","title":"Hippias Major","count":1},{"work":"Phaedo","title":"Phaedo","count":1},{"work":"Protagoras","title":"Protagoras","count":1}],"glosses":["disable, hinder"],"instancesByWork":[{"work":"Laws","title":"Laws","count":40,"shown":40,"books":[{"book":1,"chapters":[{"chapter":"?","bekker":"","instances":[["636a",8,"βλάπτον"]]}]},{"book":2,"chapters":[{"chapter":"?","bekker":"","instances":[["667e",7,"βλάπτῃ"],["669b",8,"βλάπτοιτο"]]}]},{"book":4,"chapters":[{"chapter":"?","bekker":"","instances":[["719b",7,"βλάπτοιεν"]]}]},{"book":5,"chapters":[{"chapter":"?","bekker":"","instances":[["727c",1,"βλάπτει"],["727b",3,"βλάπτει"]]}]},{"book":6,"chapters":[{"chapter":"?","bekker":"","instances":[["754c",3,"βλάπτει"],["767e",6,"βλαφθέντι"],["769b",6,"ἐβλάβης"]]}]},{"book":7,"chapters":[{"chapter":"?","bekker":"","instances":[["820d",5,"βλάψει"]]}]},{"book":8,"chapters":[{"chapter":"?","bekker":"","instances":[["843c",4,"βλάπτειν"],["843d",2,"βλαφθέντι"],["844c",3,"βλάπτῃ"],["844c",4,"βλάπτῃ"],["844d",2,"βλαφθέντι"],["845e",4,"βλαπτόμενος"],["845e",6,"βλάπτων"],["844a",7,"βλάπτων"],["846a",5,"βλάπτῃ"],["846b",4,"βλαφθέντι"]]}]},{"book":9,"chapters":[{"chapter":"?","bekker":"","instances":[["863e",8,"βλάπτῃ"],["875d",6,"βλάψαντα"],["878c",5,"βλάπτῃ"],["862b",4,"βλάπτῃ"],["862b",6,"βλαβὲν"],["877b",3,"βλαφθέντι"],["882b",2,"βλάπτων"]]}]},{"book":10,"chapters":[{"chapter":"?","bekker":"","instances":[["904b",3,"βλάπτειν"]]}]},{"book":11,"chapters":[{"chapter":"?","bekker":"","instances":[["920c",7,"βλάπτοι"],["933e",2,"βλάπτοντι"],["933e",10,"βλαβέν"],["936c",8,"βλάψῃ"],["936d",1,"βλαβέντος"],["936d",2,"βλάψαντος"],["936d",3,"βλάψαντ'"],["936d",4,"βλάψαντος"],["936d",5,"βλαβέντος"],["936d",7,"βλαβῆναι"],["933a",3,"βλάπτειν"],["933a",5,"βλάπτονται"]]}]}]},{"work":"Republic","title":"Republic","count":25,"shown":25,"books":[{"book":1,"chapters":[{"chapter":"?","bekker":"","instances":[["332e",4,"βλάπτειν"],["334d",1,"βλάπτειν"],["334d",9,"βλάπτειν"],["334e",1,"βλάπτειν"],["335c",1,"βλαπτομένους"],["335c",6,"βλαπτομένους"],["335d",7,"βλάπτειν"],["335d",11,"βλάπτειν"],["335e",5,"βλάπτειν"],["334b",9,"βλάπτειν"],["335a",10,"βλάπτειν"],["335b",2,"βλάπτειν"],["335b",5,"βλάπτειν"],["335b",6,"Βλαπτόμενοι"],["335b",10,"βλαπτόμενοι"],["336a",3,"βλάπτειν"]]}]},{"book":2,"chapters":[{"chapter":"?","bekker":"","instances":[["362c",1,"βλάπτειν"],["364c",3,"βλάψει"],["367d",4,"βλάπτει"],["379b",5,"βλάπτει"],["379b",7,"βλάπτει"]]}]},{"book":3,"chapters":[{"chapter":"?","bekker":"","instances":[["407d",4,"βλάπτοι"],["391a",6,"ἔβλαψάς"]]}]},{"book":4,"chapters":[{"chapter":"?","bekker":"","instances":[["434a",7,"βλάψαι"]]}]},{"book":8,"chapters":[{"chapter":"?","bekker":"","instances":[["553b",4,"βλαπτόμενον"]]}]}]},{"work":"Meno","title":"Meno","count":12,"shown":12,"books":[{"book":1,"chapters":[{"chapter":"?","bekker":"","instances":[["77d",2,"βλάπτει"],["77d",4,"βλάπτει"],["77e",6,"βλάπτειν"],["77e",7,"βλαβήσονται"],["78a",1,"βλαπτομένους"],["78a",2,"βλάπτονται"],["84b",7,"ἐβλάψαμεν"],["88a",2,"βλάπτειν"],["88a",4,"βλάπτει"],["88a",5,"βλάπτει"],["88b",3,"βλάπτει"],["88b",5,"βλάπτεται"]]}]}]},{"work":"Apology","title":"Apology","count":7,"shown":7,"books":[{"book":1,"chapters":[{"chapter":"?","bekker":"","instances":[["25d",1,"βλάπτεσθαι"],["25d",3,"βλάπτεσθαι"],["30c",7,"βλάψετε"],["30c",8,"βλάψειεν"],["30d",1,"βλάπτεσθαι"],["41d",8,"βλάπτειν"],["38b",2,"ἐβλάβην"]]}]}]},{"work":"Alcibiades2","title":"Alcibiades II","count":5,"shown":5,"books":[{"book":1,"chapters":[{"chapter":"?","bekker":"","instances":[["141d",1,"βλάπτεσθαι"],["142d",1,"βλάπτει"],["144d",6,"βλάπτειν"],["146d",5,"βλάπτεσθαι"],["146e",2,"βλάπτειν"]]}]}]},{"work":"Hipparchus","title":"Hipparchus","count":4,"shown":4,"books":[{"book":1,"chapters":[{"chapter":"?","bekker":"","instances":[["227e",1,"βλαβήσεσθαι"],["227e",3,"Βλαβήσεσθαι"],["227a",6,"Βλάπτονται"],["227a",7,"Βλάπτονται"]]}]}]},{"work":"Letters","title":"Letters","count":4,"shown":4,"books":[{"book":1,"chapters":[{"chapter":"?","bekker":"","instances":[["335c",5,"ἔβλαψαν"],["335e",1,"ἔβλαψεν"],["348d",1,"βλάπτοντα"],["362a",7,"βλάψαι"]]}]}]},{"work":"Lysis","title":"Lysis","count":3,"shown":3,"books":[{"book":1,"chapters":[{"chapter":"?","bekker":"","instances":[["220c",7,"βλάπτοι"],["206b",7,"βλάπτοντα"],["221a",6,"βλάπτεσθαι"]]}]}]},{"work":"Alcibiades1","title":"Alcibiades I","count":2,"shown":2,"books":[{"book":1,"chapters":[{"chapter":"?","bekker":"","instances":[["114e",11,"βλαβήσεσθαι"],["120d",4,"βλαβήσεσθαι"]]}]}]},{"work":"Clitophon","title":"Clitophon","count":2,"shown":2,"books":[{"book":1,"chapters":[{"chapter":"?","bekker":"","instances":[["410a",8,"βλάπτειν"],["410b",1,"βλάπτειν"]]}]}]},{"work":"Cratylus","title":"Cratylus","count":2,"shown":2,"books":[{"book":1,"chapters":[{"chapter":"?","bekker":"","instances":[["417d",10,"βλάπτον"],["417e",1,"βλάπτον"]]}]}]},{"work":"Gorgias","title":"Gorgias","count":2,"shown":2,"books":[{"book":1,"chapters":[{"chapter":"?","bekker":"","instances":[["475d",6,"βλαβήσῃ"],["511e",8,"ἔβλαψεν"]]}]}]},{"work":"HippiasMinor","title":"Hippias Minor","count":2,"shown":2,"books":[{"book":1,"chapters":[{"chapter":"?","bekker":"","instances":[["372d",5,"βλάπτοντες"],["373a",5,"βλαβήσεσθαι"]]}]}]},{"work":"Philebus","title":"Philebus","count":2,"shown":2,"books":[{"book":1,"chapters":[{"chapter":"?","bekker":"","instances":[["62d",2,"βλάπτοιτο"],["13a",6,"βλάψει"]]}]}]},{"work":"HippiasMajor","title":"Hippias Major","count":1,"shown":1,"books":[{"book":1,"chapters":[{"chapter":"?","bekker":"","instances":[["284d",3,"βλάπτει"]]}]}]},{"work":"Phaedo","title":"Phaedo","count":1,"shown":1,"books":[{"book":1,"chapters":[{"chapter":"?","bekker":"","instances":[["107d",4,"βλάπτειν"]]}]}]},{"work":"Protagoras","title":"Protagoras","count":1,"shown":1,"books":[{"book":1,"chapters":[{"chapter":"?","bekker":"","instances":[["314b",3,"βεβλαμμένον"]]}]}]}],"truncated":false}