{"slug":"diakybernao","key":"diaku^berna/w","head":"διακυβερνάω","lemmaBeta":"diakuberna/w","count":5,"byWork":[{"work":"Laws","title":"Laws","count":1},{"work":"Philebus","title":"Philebus","count":1},{"work":"Republic","title":"Republic","count":1},{"work":"Statesman","title":"Statesman","count":1},{"work":"Timaeus","title":"Timaeus","count":1}],"glosses":["steer through, pilot"],"instancesByWork":[{"work":"Laws","title":"Laws","count":1,"shown":1,"books":[{"book":4,"chapters":[{"chapter":"?","bekker":"","instances":[["709b",8,"διακυβερνῶσι"]]}]}]},{"work":"Philebus","title":"Philebus","count":1,"shown":1,"books":[{"book":1,"chapters":[{"chapter":"?","bekker":"","instances":[["28d",9,"διακυβερνᾶν"]]}]}]},{"work":"Republic","title":"Republic","count":1,"shown":1,"books":[{"book":9,"chapters":[{"chapter":"?","bekker":"","instances":[["573d",4,"διακυβερνᾷ"]]}]}]},{"work":"Statesman","title":"Statesman","count":1,"shown":1,"books":[{"book":1,"chapters":[{"chapter":"?","bekker":"","instances":[["301d",5,"διακυβερνῶντα"]]}]}]},{"work":"Timaeus","title":"Timaeus","count":1,"shown":1,"books":[{"book":1,"chapters":[{"chapter":"?","bekker":"","instances":[["42e",3,"διακυβερνᾶν"]]}]}]}],"truncated":false}