{"slug":"epanagkes","key":"e)pa^na/gkhs","head":"ἐπανάγκης","lemmaBeta":"e)pana/gkhs","count":10,"byWork":[{"work":"Laws","title":"Laws","count":8},{"work":"Republic","title":"Republic","count":1},{"work":"Symposium","title":"Symposium","count":1}],"glosses":["it is compulsory, necessary"],"instancesByWork":[{"work":"Laws","title":"Laws","count":8,"shown":8,"books":[{"book":6,"chapters":[{"chapter":"?","bekker":"","instances":[["756c",8,"ἐπάναγκες"],["765c",4,"ἐπάναγκες"],["764a",4,"ἐπάναγκες"],["764a",6,"ἐπάναγκες"],["765a",8,"ἐπάναγκες"]]}]},{"book":8,"chapters":[{"chapter":"?","bekker":"","instances":[["848a",8,"ἐπάναγκες"]]}]},{"book":9,"chapters":[{"chapter":"?","bekker":"","instances":[["877c",6,"ἐπάναγκες"],["878e",6,"ἐπάναγκες"]]}]}]},{"work":"Republic","title":"Republic","count":1,"shown":1,"books":[{"book":7,"chapters":[{"chapter":"?","bekker":"","instances":[["536d",7,"ἐπάναγκες"]]}]}]},{"work":"Symposium","title":"Symposium","count":1,"shown":1,"books":[{"book":1,"chapters":[{"chapter":"?","bekker":"","instances":[["176e",5,"ἐπάναγκες"]]}]}]}],"truncated":false}