{"slug":"kolakeuo","key":"kola^keu/w","head":"κολακεύω","lemmaBeta":"kolakeu/w","count":6,"byWork":[{"work":"Republic","title":"Republic","count":3},{"work":"Alcibiades1","title":"Alcibiades I","count":1},{"work":"Gorgias","title":"Gorgias","count":1},{"work":"Letters","title":"Letters","count":1}],"glosses":["to be a flatterer"],"instancesByWork":[{"work":"Republic","title":"Republic","count":3,"shown":3,"books":[{"book":7,"chapters":[{"chapter":"?","bekker":"","instances":[["538d",2,"κολακεύει"],["538b",2,"κολακεύοντας"],["539a",1,"κολακεύοντα"]]}]}]},{"work":"Alcibiades1","title":"Alcibiades I","count":1,"shown":1,"books":[{"book":1,"chapters":[{"chapter":"?","bekker":"","instances":[["120b",5,"κολακεύσοντες"]]}]}]},{"work":"Gorgias","title":"Gorgias","count":1,"shown":1,"books":[{"book":1,"chapters":[{"chapter":"?","bekker":"","instances":[["521b",1,"Κολακεύσοντα"]]}]}]},{"work":"Letters","title":"Letters","count":1,"shown":1,"books":[{"book":1,"chapters":[{"chapter":"?","bekker":"","instances":[["331c",4,"κολακεύοντά"]]}]}]}],"truncated":false}