{"slug":"mythologeo","key":"mu_qologe/w","head":"μυθολογέω","lemmaBeta":"muqologe/w","count":17,"byWork":[{"work":"Republic","title":"Republic","count":9},{"work":"Gorgias","title":"Gorgias","count":2},{"work":"HippiasMajor","title":"Hippias Major","count":1},{"work":"Laws","title":"Laws","count":1},{"work":"Letters","title":"Letters","count":1},{"work":"Phaedo","title":"Phaedo","count":1},{"work":"Phaedrus","title":"Phaedrus","count":1},{"work":"Timaeus","title":"Timaeus","count":1}],"glosses":["tell mythic tales"],"instancesByWork":[{"work":"Republic","title":"Republic","count":9,"shown":9,"books":[{"book":2,"chapters":[{"chapter":"?","bekker":"","instances":[["359d",6,"μυθολογοῦσιν"],["376d",9,"μυθολογοῦντές"],["378e",3,"μεμυθολογημένα"],["380c",2,"μυθολογοῦντα"],["379a",2,"μυθολογεῖν"]]}]},{"book":3,"chapters":[{"chapter":"?","bekker":"","instances":[["392b",6,"μυθολογεῖν"],["415a",3,"μυθολογοῦντες"]]}]},{"book":6,"chapters":[{"chapter":"?","bekker":"","instances":[["501e",4,"μυθολογοῦμεν"]]}]},{"book":9,"chapters":[{"chapter":"?","bekker":"","instances":[["588c",2,"μυθολογοῦνται"]]}]}]},{"work":"Gorgias","title":"Gorgias","count":2,"shown":2,"books":[{"book":1,"chapters":[{"chapter":"?","bekker":"","instances":[["493d",3,"μυθολογῶ"],["493a",5,"μυθολογῶν"]]}]}]},{"work":"HippiasMajor","title":"Hippias Major","count":1,"shown":1,"books":[{"book":1,"chapters":[{"chapter":"?","bekker":"","instances":[["286a",2,"μυθολογῆσαι"]]}]}]},{"work":"Laws","title":"Laws","count":1,"shown":1,"books":[{"book":3,"chapters":[{"chapter":"?","bekker":"","instances":[["682e",5,"μυθολογεῖτέ"]]}]}]},{"work":"Letters","title":"Letters","count":1,"shown":1,"books":[{"book":1,"chapters":[{"chapter":"?","bekker":"","instances":[["352e",1,"μυθολογοῦντες"]]}]}]},{"work":"Phaedo","title":"Phaedo","count":1,"shown":1,"books":[{"book":1,"chapters":[{"chapter":"?","bekker":"","instances":[["61e",2,"μυθολογεῖν"]]}]}]},{"work":"Phaedrus","title":"Phaedrus","count":1,"shown":1,"books":[{"book":1,"chapters":[{"chapter":"?","bekker":"","instances":[["276e",3,"μυθολογοῦντα"]]}]}]},{"work":"Timaeus","title":"Timaeus","count":1,"shown":1,"books":[{"book":1,"chapters":[{"chapter":"?","bekker":"","instances":[["22b",1,"μυθολογεῖν"]]}]}]}],"truncated":false}