{"slug":"pammegethes","key":"pammege/qhs","head":"παμμεγέθης","lemmaBeta":"pammege/qhs","count":3,"byWork":[{"work":"Parmenides","title":"Parmenides","count":2},{"work":"Laws","title":"Laws","count":1}],"glosses":[],"instancesByWork":[{"work":"Parmenides","title":"Parmenides","count":2,"shown":2,"books":[{"book":1,"chapters":[{"chapter":"?","bekker":"","instances":[["164d",4,"παμμέγεθες"],["128b",3,"παμμεγέθη"]]}]}]},{"work":"Laws","title":"Laws","count":1,"shown":1,"books":[{"book":11,"chapters":[{"chapter":"?","bekker":"","instances":[["913d",3,"παμμέγεθες"]]}]}]}],"truncated":false}