{"slug":"pollaplasios","key":"pollapla^/sios","head":"πολλαπλάσιος","lemmaBeta":"pollapla/sios","count":6,"byWork":[{"work":"Republic","title":"Republic","count":4},{"work":"Letters","title":"Letters","count":1},{"work":"Statesman","title":"Statesman","count":1}],"glosses":["many"],"instancesByWork":[{"work":"Republic","title":"Republic","count":4,"shown":4,"books":[{"book":4,"chapters":[{"chapter":"?","bekker":"","instances":[["423b",1,"πολλαπλασίας"]]}]},{"book":7,"chapters":[{"chapter":"?","bekker":"","instances":[["530c",2,"πολλαπλάσιον"],["534a",7,"πολλαπλασίων"]]}]},{"book":8,"chapters":[{"chapter":"?","bekker":"","instances":[["555e",5,"πολλαπλασίους"]]}]}]},{"work":"Letters","title":"Letters","count":1,"shown":1,"books":[{"book":1,"chapters":[{"chapter":"?","bekker":"","instances":[["333a",1,"πολλαπλασίαν"]]}]}]},{"work":"Statesman","title":"Statesman","count":1,"shown":1,"books":[{"book":1,"chapters":[{"chapter":"?","bekker":"","instances":[["300b",4,"πολλαπλάσιον"]]}]}]}],"truncated":false}