{"slug":"sophron","key":"sw/frwn","head":"σώφρων","lemmaBeta":"sw/frwn","count":134,"byWork":[{"work":"Laws","title":"Laws","count":31},{"work":"Charmides","title":"Charmides","count":23},{"work":"Republic","title":"Republic","count":20},{"work":"Gorgias","title":"Gorgias","count":11},{"work":"Letters","title":"Letters","count":7},{"work":"Statesman","title":"Statesman","count":7},{"work":"Alcibiades1","title":"Alcibiades I","count":6},{"work":"Meno","title":"Meno","count":4},{"work":"Protagoras","title":"Protagoras","count":4},{"work":"Epinomis","title":"Epinomis","count":3},{"work":"Phaedrus","title":"Phaedrus","count":3},{"work":"Philebus","title":"Philebus","count":3},{"work":"Euthydemus","title":"Euthydemus","count":2},{"work":"Symposium","title":"Symposium","count":2},{"work":"Timaeus","title":"Timaeus","count":2},{"work":"Lovers","title":"Lovers","count":1},{"work":"Lysis","title":"Lysis","count":1},{"work":"Menexenus","title":"Menexenus","count":1},{"work":"Phaedo","title":"Phaedo","count":1},{"work":"Sophist","title":"Sophist","count":1},{"work":"Theaetetus","title":"Theaetetus","count":1}],"glosses":["of sound mind"],"instancesByWork":[{"work":"Laws","title":"Laws","count":31,"shown":31,"books":[{"book":1,"chapters":[{"chapter":"?","bekker":"","instances":[["631c",7,"σώφρων"],["647d",3,"σώφρων"]]}]},{"book":2,"chapters":[{"chapter":"?","bekker":"","instances":[["660e",3,"σώφρων"],["665e",3,"σωφρονέστερος"],["660a",6,"σωφρόνων"]]}]},{"book":3,"chapters":[{"chapter":"?","bekker":"","instances":[["679e",3,"σωφρονέστεροι"],["685a",8,"σώφρονα"],["692a",1,"σώφρονα"],["696b",10,"σώφρονα"]]}]},{"book":4,"chapters":[{"chapter":"?","bekker":"","instances":[["710c",5,"σώφρων"],["711d",6,"σωφρόνων"],["716d",1,"σώφρων"],["716d",2,"σώφρων"],["717d",7,"σωφρονεστάτη"]]}]},{"book":5,"chapters":[{"chapter":"?","bekker":"","instances":[["728e",3,"σωφρονέστατα"],["733e",3,"σώφρονα"],["733e",6,"σώφρονα"],["734c",4,"σώφρων"],["734d",2,"σώφρονα"],["737d",1,"σώφρονας"],["734a",6,"σώφρονι"]]}]},{"book":6,"chapters":[{"chapter":"?","bekker":"","instances":[["772a",3,"σώφρονος"]]}]},{"book":7,"chapters":[{"chapter":"?","bekker":"","instances":[["802c",8,"σώφρονι"],["802e",10,"σῶφρον"],["808c",5,"σώφροσιν"],["814e",8,"σώφρονος"]]}]},{"book":8,"chapters":[{"chapter":"?","bekker":"","instances":[["836d",7,"σώφρονος"],["837c",7,"σῶφρον"]]}]},{"book":9,"chapters":[{"chapter":"?","bekker":"","instances":[["870c",1,"σωφρόνως"]]}]},{"book":10,"chapters":[{"chapter":"?","bekker":"","instances":[["909a",7,"σωφρόνων"]]}]},{"book":11,"chapters":[{"chapter":"?","bekker":"","instances":[["936d",2,"σώφρονα"]]}]}]},{"work":"Charmides","title":"Charmides","count":23,"shown":23,"books":[{"book":1,"chapters":[{"chapter":"?","bekker":"","instances":[["157d",6,"σωφρονέστατος"],["158d",1,"σώφρων"],["158d",4,"σώφρων"],["159d",11,"σωφρονέστερον"],["160d",1,"σωφρονέστερος"],["160e",9,"σώφρονες"],["163c",8,"σώφρονα"],["164c",2,"σωφρόνως"],["164c",6,"σωφρόνως"],["170e",4,"σώφρων"],["171c",2,"σώφρων"],["171d",3,"σώφρων"],["171d",6,"σώφροσιν"],["175c",2,"σώφρων"],["175e",1,"σωφρονέστατος"],["158b",6,"σώφρων"],["159b",8,"σώφρονας"],["160b",8,"σώφρων"],["160b",9,"σώφρονα"],["162a",4,"σωφρόνως"],["167a",1,"σώφρων"],["171a",3,"σώφρων"],["176a",4,"σωφρονέστερος"]]}]}]},{"work":"Republic","title":"Republic","count":20,"shown":20,"books":[{"book":1,"chapters":[{"chapter":"?","bekker":"","instances":[["331e",9,"σωφρόνως"],["332a",5,"σωφρόνως"]]}]},{"book":3,"chapters":[{"chapter":"?","bekker":"","instances":[["391c",2,"σωφρονεστάτου"],["395c",5,"σώφρονας"],["399c",3,"σωφρόνων"],["410e",10,"σώφρων"],["416d",8,"σώφρονές"],["399b",8,"σωφρόνως"],["401a",7,"σώφρονός"],["403a",7,"σωφρόνως"]]}]},{"book":4,"chapters":[{"chapter":"?","bekker":"","instances":[["427e",10,"σώφρων"],["431d",7,"σώφρονα"],["442c",10,"σώφρονα"],["443e",2,"σώφρονα"],["423a",6,"σωφρόνως"],["431b",7,"σῶφρον"],["435b",6,"σώφρων"]]}]},{"book":6,"chapters":[{"chapter":"?","bekker":"","instances":[["485e",3,"Σώφρων"],["501b",2,"σῶφρον"]]}]},{"book":9,"chapters":[{"chapter":"?","bekker":"","instances":[["571d",7,"σωφρόνως"]]}]}]},{"work":"Gorgias","title":"Gorgias","count":11,"shown":11,"books":[{"book":1,"chapters":[{"chapter":"?","bekker":"","instances":[["491d",10,"σώφρονα"],["491e",2,"σώφρονας"],["493d",7,"σώφρονος"],["507c",1,"σώφρονα"],["507c",6,"σώφρονι"],["507a",1,"σώφρων"],["507a",1,"σώφρων"],["507a",5,"σώφρων"],["507a",6,"σώφρονι"],["507a",7,"σώφρων"],["507b",5,"σώφρονος"]]}]}]},{"work":"Letters","title":"Letters","count":7,"shown":7,"books":[{"book":1,"chapters":[{"chapter":"?","bekker":"","instances":[["326c",4,"σώφρων"],["332e",2,"σώφρονα"],["336c",3,"σώφρονα"],["351d",2,"σώφρων"],["354e",6,"σώφροσιν"],["336b",1,"σώφρονος"],["359a",6,"σώφρων"]]}]}]},{"work":"Statesman","title":"Statesman","count":7,"shown":7,"books":[{"book":1,"chapters":[{"chapter":"?","bekker":"","instances":[["307c",3,"σώφρονα"],["308e",9,"σώφρονος"],["309e",6,"σῶφρον"],["310d",7,"σώφρονι"],["310e",9,"σώφρονα"],["311a",7,"σωφρόνων"],["311b",9,"σωφρόνων"]]}]}]},{"work":"Alcibiades1","title":"Alcibiades I","count":6,"shown":6,"books":[{"book":1,"chapters":[{"chapter":"?","bekker":"","instances":[["121e",7,"σωφρονέστατος"],["133c",21,"σώφρονες"],["134d",1,"σωφρόνως"],["122a",4,"σωφρονέστατος"],["131b",5,"σώφρων"],["134a",13,"σώφρων"]]}]}]},{"work":"Meno","title":"Meno","count":4,"shown":4,"books":[{"book":1,"chapters":[{"chapter":"?","bekker":"","instances":[["73a",9,"σωφρόνως"],["73b",1,"σωφρόνως"],["73b",7,"σώφρονες"],["96a",1,"σαόφροσιν"]]}]}]},{"work":"Protagoras","title":"Protagoras","count":4,"shown":4,"books":[{"book":1,"chapters":[{"chapter":"?","bekker":"","instances":[["332d",5,"σωφρόνως"],["332d",6,"σωφρόνως"],["332b",4,"σωφρόνως"],["332b",5,"σωφρόνως"]]}]}]},{"work":"Epinomis","title":"Epinomis","count":3,"shown":3,"books":[{"book":1,"chapters":[{"chapter":"?","bekker":"","instances":[["979c",7,"σώφρονα"],["988c",3,"σώφροσιν"],["992c",7,"σώφρονες"]]}]}]},{"work":"Phaedrus","title":"Phaedrus","count":3,"shown":3,"books":[{"book":1,"chapters":[{"chapter":"?","bekker":"","instances":[["273e",6,"σώφρονα"],["279c",3,"σώφρων"],["245b",4,"σώφρονα"]]}]}]},{"work":"Philebus","title":"Philebus","count":3,"shown":3,"books":[{"book":1,"chapters":[{"chapter":"?","bekker":"","instances":[["19c",2,"σώφρονι"],["45d",4,"σώφρονι"],["45d",7,"σώφρονάς"]]}]}]},{"work":"Euthydemus","title":"Euthydemus","count":2,"shown":2,"books":[{"book":1,"chapters":[{"chapter":"?","bekker":"","instances":[["281c",6,"σώφρων"],["279b",5,"σώφρονά"]]}]}]},{"work":"Symposium","title":"Symposium","count":2,"shown":2,"books":[{"book":1,"chapters":[{"chapter":"?","bekker":"","instances":[["188a",5,"σώφρονα"],["214b",4,"σωφρονεστάτου"]]}]}]},{"work":"Timaeus","title":"Timaeus","count":2,"shown":2,"books":[{"book":1,"chapters":[{"chapter":"?","bekker":"","instances":[["18b",4,"σώφροσιν"],["72a",5,"σώφρονι"]]}]}]},{"work":"Lovers","title":"Lovers","count":1,"shown":1,"books":[{"book":1,"chapters":[{"chapter":"?","bekker":"","instances":[["138c",8,"σώφρων"]]}]}]},{"work":"Lysis","title":"Lysis","count":1,"shown":1,"books":[{"book":1,"chapters":[{"chapter":"?","bekker":"","instances":[["216b",5,"σῶφρον"]]}]}]},{"work":"Menexenus","title":"Menexenus","count":1,"shown":1,"books":[{"book":1,"chapters":[{"chapter":"?","bekker":"","instances":[["248a",4,"σώφρων"]]}]}]},{"work":"Phaedo","title":"Phaedo","count":1,"shown":1,"books":[{"book":1,"chapters":[{"chapter":"?","bekker":"","instances":[["68e",3,"σώφρονές"]]}]}]},{"work":"Sophist","title":"Sophist","count":1,"shown":1,"books":[{"book":1,"chapters":[{"chapter":"?","bekker":"","instances":[["230d",5,"σωφρονεστάτη"]]}]}]},{"work":"Theaetetus","title":"Theaetetus","count":1,"shown":1,"books":[{"book":1,"chapters":[{"chapter":"?","bekker":"","instances":[["210c",3,"σωφρόνως"]]}]}]}],"truncated":false}